dopt/__init__.py
dopt/client.py
dopt/core/__init__.py
dopt/core/api_error.py
dopt/core/datetime_utils.py
dopt/core/jsonable_encoder.py
dopt/core/remove_none_from_headers.py
dopt/environment.py
dopt/errors/__init__.py
dopt/errors/bad_request_error.py
dopt/errors/internal_server_error.py
dopt/errors/unauthorized_error.py
dopt/py.typed
dopt/types/__init__.py
dopt/types/bad_request_error_response_body.py
dopt/types/bad_request_error_response_body_code.py
dopt/types/identify_batch_request_body.py
dopt/types/identify_batch_request_body_item.py
dopt/types/identify_batch_request_body_item_groups_item.py
dopt/types/identify_batch_response_body.py
dopt/types/identify_request_body.py
dopt/types/identify_request_params.py
dopt/types/identify_segment_request_body.py
dopt/types/identify_segment_request_body_identify_segment_request_body.py
dopt/types/identify_segment_response_body.py
dopt/types/identify_user_request_body_groups_item.py
dopt/types/internal_server_error_response_body.py
dopt/types/not_found_error_response_body.py
dopt/types/segment_common.py
dopt/types/segment_group.py
dopt/types/segment_identify.py
dopt/types/timeout_error_response_body.py
dopt/types/unauthorized_error_response_body.py
fern_dopt_users-0.0.10.dist-info/METADATA
fern_dopt_users-0.0.10.dist-info/WHEEL
fern_dopt_users-0.0.10.dist-info/RECORD
